setup.py
richard_distributions/Binomialdistribution.py
richard_distributions/Gaussiandistribution.py
richard_distributions/Generaldistribution.py
richard_distributions/__init__.py
richard_distributions.egg-info/PKG-INFO
richard_distributions.egg-info/SOURCES.txt
richard_distributions.egg-info/dependency_links.txt
richard_distributions.egg-info/not-zip-safe
richard_distributions.egg-info/top_level.txt