Metadata-Version: 1.0
Name: richard-distributions
Version: 0.3
Summary: Gaussian distributions
Home-page: UNKNOWN
Author: Richard Valenzuela Castro
Author-email: valenz.richards@gmail.com
License: UNKNOWN
Platform: UNKNOWN
